{
   "travels": [{
      "id": 101,
      "travelName": "Argentina",
      "destinations": [{
            "id": 1,
            "name": "Villa Carlos Paz",
            "description": "Disfruta de las vacaciones de invierno en Villa Carlos paz! Hotel con piscina climatizada y media pensión, veni a decifrutar de este hermoso lugar en familia.",
            "date": "17 de Julio - Salida grupal",
            "price": "U$S 395",
            "priceType": "Por persona en base doble",
            "includes": [
               "Viaje terrestre en omnibus",
               "4 noches de hotel media pensión",
               "Servicios del hotel: Piscina climatizad cubierta y externa, Solarium, Sauna",
               "Gimnasio, cancha de futbol 5, WI-fi",
               "Desayuno Buffet",
               "Servicio a bordo",
               "Coordinador acompañante"
            ],
            "tours": [
               "Tour Villa General Belgrano",
               "Tour por el Lago San Roque",
               "Tour por Cordoba y Carlos Paz",
               "Visita a Multiparque Pekos"
            ],
            "image": "carlos-paz-1.jpg"
         },
         {
            "id": 2,
            "name": "Ushuaia y Calafate",
            "description": "Nos vamos al fin del mundo. Veni con nosotros y disfruta de este hermoso viaje.",
            "date": "7 de Junio - Salida grupal",
            "price": "U$S 1350",
            "priceType": "Por persona en base doble",
            "includes": [
               "Viaje terrestre en omnibus",
               "4 noches de hotel media pensión",
               "Servicios del hotel: Piscina climatizad cubierta y externa, Solarium, Sauna",
               "Gimnasio, cancha de futbol 5, WI-fi",
               "Desayuno Buffet",
               "Servicio a bordo",
               "Coordinador acompañante"
            ],
            "tours": [
               "Tour Villa General Belgrano",
               "Tour por el Lago San Roque",
               "Tour por Cordoba y Carlos Paz",
               "Visita a Multiparque Pekos"
            ],
            "image": "ushuaia-calafate-1.jpg"
         },
         {
            "id": 3,
            "name": "Bariloche",
            "description": "Bariloche no es solo para los chicos!",
            "date": "12 de Agosto - Salida grupal",
            "price": "U$S 740",
            "priceType": "Por persona en base doble",
            "includes": [
               "Salida desde Artigas en Bus semi cama",
               "1 noche de hotel en Buenos Aires",
               "1 noche de hotel en Neuquen",
               "4 noches de hotel en Bariloche",
               "Seguro de viaje",
               "Guia local en todo el recorrido",
               "Coordinador acompañante"
            ],
            "tours": [
               "Tour Villa General Belgrano",
               "Tour por el Lago San Roque",
               "Tour por Cordoba y Carlos Paz",
               "Visita a Multiparque Pekos"
            ],
            "image": "bariloche-1.webp"
         },
         {
            "id": 4,
            "name": "Norte Argentino",
            "description": "Sin texto",
            "date": "19 de Mayo - Salida grupal",
            "price": "U$S 590",
            "priceType": "Por persona en base doble",
            "includes": [
               "Salida desde Artigas en Bus semi cama",
               "1 noche de hotel en Tafi del Valle con media pension",
               "3 noches de hotel en Salta con media pension",
               "1 noches de hotel en Tucuman con media pension",
               "Seguro de viaje",
               "Guia local en todo el recorrido",
               "Coordinador acompañante"
            ],
            "tours": [
               "City Tour en Salta",
               "Visitas a: Purmarca (cerro de los 7 colores), Humahuaca, Salinas Grandes, Cafayate",
               "Tour por Cordoba y Carlos Paz",
               "Viñedos: Tilcara, Salta, San Miguel de Tucuman"
            ],
            "image": "norte-argentino-1.webp"
         }
      ]
   }]
}